hide/__init__.py
hide/client/__init__.py
hide/client/hide_client.py
hide/devcontainer/__init__.py
hide/devcontainer/model.py
hide/langchain/__init__.py
hide/langchain/toolkit.py
hide/model.py
hide/toolkit/__init__.py
hide/toolkit/toolkit.py
hide_py-0.5.3.dist-info/LICENSE
hide_py-0.5.3.dist-info/METADATA
hide_py-0.5.3.dist-info/WHEEL
hide_py-0.5.3.dist-info/RECORD
