Metadata-Version: 2.1
Name: hide-py
Version: 0.5.3
Summary: Hide: Headless IDE for coding agents
Home-page: https://hide.sh
License: MIT
Author: Art Moskvin
Author-email: amoskvin@me.com
Requires-Python: >=3.10,<4.0
Classifier: License :: OSI Approved :: MIT License
Classifier: Programming Language :: Python :: 3
Classifier: Programming Language :: Python :: 3.10
Classifier: Programming Language :: Python :: 3.11
Classifier: Programming Language :: Python :: 3.12
Classifier: Programming Language :: Python :: 3.13
Requires-Dist: langchain (>=0.1.16,<0.2.0)
Requires-Dist: langchain-openai (>=0.1.3,<0.2.0)
Requires-Dist: langchainhub (>=0.1.15,<0.2.0)
Requires-Dist: pydantic (>=2.7.3,<3.0.0)
Requires-Dist: pyjson5 (>=1.6.6,<2.0.0)
Requires-Dist: requests (>=2.31.0,<3.0.0)
Project-URL: Documentation, https://hide.sh
Project-URL: Repository, https://github.com/artmoskvin/hide-python
